TheWildTool/TWTErrors.py
TheWildTool/WorkData.py
TheWildTool/__init__.py
TheWildTool-1.5.7.dist-info/LICENSE
TheWildTool-1.5.7.dist-info/METADATA
TheWildTool-1.5.7.dist-info/WHEEL
TheWildTool-1.5.7.dist-info/top_level.txt
TheWildTool-1.5.7.dist-info/RECORD
