Metadata-Version: 2.1
Name: TheWildTool
Version: 1.5.7
Summary: TheWildTool is a tool developed with the main objective of saving time when working with audio datasets. Either to prepare them, to get them or to train a model with them. 🤖
Home-page: https://github.com/ElHaban3ro/ConvTool
Author: ElHaban3ro
Author-email: habanferd@gmail.com
License: MIT
Keywords: Data Analysis,IA,datasets,Data Engenering,DeepLearing
Classifier: Programming Language :: Python :: 3.10
License-File: LICENSE
Requires-Dist: moviepy (==1.0.3)
Requires-Dist: ipython
Requires-Dist: scipy
Requires-Dist: matplotlib
Requires-Dist: yt-dlp
